{
  "sections": [
    {
      "id": "economics_minor",
      "title": "Economics minor",
      "creditsRequired": 21,
      "requirements": [
        {
          "id": "economics_principles",
          "title": "Economics principles",
          "description": "Take the following courses",
          "creditsRequired": 6,
          "rule": {
            "type": "take_courses",
            "courses": [
              "ECON 1010",
              "ECON 1020"
            ]
          }
        },
        {
          "id": "statistics",
          "title": "Statistics",
          "description": "Choose a statistics option",
          "creditsRequired": 3,
          "rule": {
            "type": "group",
            "operator": "OR",
            "rules": [
              {
                "type": "take_from_list",
                "count": 1,
                "countType": "courses",
                "description": "Choose a course",
                "courses": [
                  "ECON 1500",
                  "ECON 1510"
                ]
              },
              {
                "type": "group",
                "operator": "AND",
                "rules": [
                  {
                    "type": "take_courses",
                    "description": "Take the following course",
                    "courses": [
                      "MATH 2820L"
                    ]
                  },
                  {
                    "type": "take_from_list",
                    "count": 1,
                    "countType": "courses",
                    "description": "Choose a course",
                    "courses": [
                      "MATH 2810",
                      "MATH 2820"
                    ]
                  }
                ]
              }
            ]
          }
        },
        {
          "id": "microeconomics",
          "title": "Microeconomics",
          "description": "Take the following course",
          "creditsRequired": 3,
          "rule": {
            "type": "take_courses",
            "courses": [
              "ECON 3012"
            ]
          }
        },
        {
          "id": "economics_electives",
          "title": "Economics electives",
          "description": "Choose from economics courses",
          "creditsRequired": 9,
          "rule": {
            "type": "take_any_courses",
            "credits": 9,
            "filter": {
              "type": "subject_number",
              "subjects": [
                "ECON"
              ]
            }
          },
          "constraintsStructured": [
            {
              "id": "course_number_range_at_least_one_course_must_be_above_econ_3",
              "type": "course_number_range",
              "description": "At least one course must be above ECON 3015",
              "subjectCode": "ECON",
              "minNumber": 3015,
              "minCount": 1,
              "operator": "above"
            }
          ]
        }
      ]
    }
  ]
}